excodemllab/__init__.py
excodemllab/abalone.py
excodemllab/abalone2.py
excodemllab/cifar.py
excodemllab/kmeans.py
excodemllab/liner_model.py
excodemllab/liner_models.py
excodemllab/mnist.py
excodemllab/movie_review.py
excodemllab/ploteley.py
excodemllab/plotely.py
excodemllab/spam.py
excodemllab-0.1.3.dist-info/licenses/LICENSE
tests/test_basic.py
excodemllab-0.1.3.dist-info/METADATA
excodemllab-0.1.3.dist-info/WHEEL
excodemllab-0.1.3.dist-info/top_level.txt
excodemllab-0.1.3.dist-info/RECORD
